fknni/__init__.py
fknni/knn/__init__.py
fknni/knn/knn.py
fknni-1.3.0.dist-info/licenses/LICENSE
fknni-1.3.0.dist-info/WHEEL
fknni-1.3.0.dist-info/METADATA
fknni-1.3.0.dist-info/RECORD
