Metadata-Version: 2.4
Name: fknni
Version: 1.3.0
Summary: Fast implementations of KNN imputation.
Author: Lukas Heumos
Maintainer-email: Lukas Heumos <lukas.heumos@posteo.net>
Requires-Python: >=3.12
Classifier: Programming Language :: Python :: 3 :: Only
Classifier: Programming Language :: Python :: 3.12
Classifier: Programming Language :: Python :: 3.13
License-File: LICENSE
Requires-Dist: array-api-compat
Requires-Dist: pandas
Requires-Dist: scikit-learn
Requires-Dist: pre-commit ; extra == "dev"
Requires-Dist: twine>=4.0.2 ; extra == "dev"
Requires-Dist: docutils>=0.8,!=0.18.*,!=0.19.* ; extra == "doc"
Requires-Dist: ipykernel ; extra == "doc"
Requires-Dist: ipython ; extra == "doc"
Requires-Dist: matplotlib ; extra == "doc"
Requires-Dist: myst-nb ; extra == "doc"
Requires-Dist: sphinx>=4 ; extra == "doc"
Requires-Dist: sphinx-autodoc-typehints ; extra == "doc"
Requires-Dist: sphinx-book-theme>=1 ; extra == "doc"
Requires-Dist: sphinx-copybutton ; extra == "doc"
Requires-Dist: sphinxcontrib-bibtex>=1 ; extra == "doc"
Requires-Dist: sphinxext-opengraph ; extra == "doc"
Requires-Dist: faiss-cpu ; extra == "faisscpu"
Requires-Dist: faiss-gpu-cu12 ; extra == "faissgpu"
Requires-Dist: cudf-cu12>=25.10 ; extra == "rapids12"
Requires-Dist: cugraph-cu12>=25.10 ; extra == "rapids12"
Requires-Dist: cuml-cu12>=25.10 ; extra == "rapids12"
Requires-Dist: cupy-cuda12x ; extra == "rapids12"
Requires-Dist: cuvs-cu12>=25.10 ; extra == "rapids12"
Requires-Dist: cudf-cu13>=25.10 ; extra == "rapids13"
Requires-Dist: cugraph-cu13>=25.10 ; extra == "rapids13"
Requires-Dist: cuml-cu13>=25.10 ; extra == "rapids13"
Requires-Dist: cupy-cuda13x ; extra == "rapids13"
Requires-Dist: cuvs-cu13>=25.10 ; extra == "rapids13"
Requires-Dist: coverage ; extra == "test"
Requires-Dist: pytest ; extra == "test"
Project-URL: Documentation, https://fknni.readthedocs.io/
Project-URL: Homepage, https://github.com/zethson/fknni
Project-URL: Source, https://github.com/zethson/fknni
Provides-Extra: dev
Provides-Extra: doc
Provides-Extra: faisscpu
Provides-Extra: faissgpu
Provides-Extra: rapids12
Provides-Extra: rapids13
Provides-Extra: test
